<?xml version="1.0" encoding="UTF-8"?>
<objects serializationModel="Studio.02.02.00">
	<object class="AudioFile" id="{3a6c19d9-62e5-4c51-828a-15fa734b3612}">
		<property name="assetPath">
			<value>1928A1-Shoot-02.wav</value>
		</property>
		<property name="frequencyInKHz">
			<value>96</value>
		</property>
		<property name="channelCount">
			<value>1</value>
		</property>
		<property name="length">
			<value>0.38296875000000002</value>
		</property>
		<relationship name="masterAssetFolder">
			<destination>{f5a0e97a-cd3f-4906-adb9-e86e23903118}</destination>
		</relationship>
	</object>
</objects>
